odoo/addons/product_supplierinfo_update_price/README.rst
odoo/addons/product_supplierinfo_update_price/__init__.py
odoo/addons/product_supplierinfo_update_price/__manifest__.py
odoo/addons/product_supplierinfo_update_price/i18n/es.po
odoo/addons/product_supplierinfo_update_price/i18n/it.po
odoo/addons/product_supplierinfo_update_price/i18n/product_supplierinfo_update_price.pot
odoo/addons/product_supplierinfo_update_price/models/__init__.py
odoo/addons/product_supplierinfo_update_price/models/purchase_order_line.py
odoo/addons/product_supplierinfo_update_price/readme/CONTRIBUTORS.md
odoo/addons/product_supplierinfo_update_price/readme/DESCRIPTION.md
odoo/addons/product_supplierinfo_update_price/readme/USAGE.md
odoo/addons/product_supplierinfo_update_price/static/description/icon.png
odoo/addons/product_supplierinfo_update_price/static/description/index.html
odoo/addons/product_supplierinfo_update_price/tests/__init__.py
odoo/addons/product_supplierinfo_update_price/tests/test_purchase_order_line.py
odoo/addons/product_supplierinfo_update_price/views/purchase_views.xml
odoo_addon_product_supplierinfo_update_price-16.0.1.0.0.6.dist-info/METADATA
odoo_addon_product_supplierinfo_update_price-16.0.1.0.0.6.dist-info/WHEEL
odoo_addon_product_supplierinfo_update_price-16.0.1.0.0.6.dist-info/top_level.txt
odoo_addon_product_supplierinfo_update_price-16.0.1.0.0.6.dist-info/RECORD
