Metadata-Version: 2.1
Name: odoo-addon-product_supplierinfo_update_price
Version: 16.0.1.0.0.6
Summary: Updates the product's vendor price with the price set in a purchase order.
Home-page: https://github.com/OCA/purchase-workflow
Author: Dixmit,Odoo Community Association (OCA)
Author-email: support@odoo-community.org
License: AGPL-3
Classifier: Programming Language :: Python
Classifier: Framework :: Odoo
Classifier: Framework :: Odoo :: 16.0
Classifier: License :: OSI Approved :: GNU Affero General Public License v3
Requires-Python: >=3.10
Requires-Dist: odoo<16.1dev,>=16.0a
